hassmart_homeassistant-0.65.4.dist-info/DESCRIPTION.rst
hassmart_homeassistant-0.65.4.dist-info/METADATA
hassmart_homeassistant-0.65.4.dist-info/RECORD
hassmart_homeassistant-0.65.4.dist-info/WHEEL
hassmart_homeassistant-0.65.4.dist-info/entry_points.txt
hassmart_homeassistant-0.65.4.dist-info/metadata.json
hassmart_homeassistant-0.65.4.dist-info/top_level.txt
homeassistant/__init__.py
homeassistant/__main__.py
homeassistant/bootstrap.py
homeassistant/config.py
homeassistant/config_entries.py
homeassistant/const.py
homeassistant/core.py
homeassistant/exceptions.py
homeassistant/loader.py
homeassistant/monkey_patch.py
homeassistant/package_constraints.txt
homeassistant/remote.py
homeassistant/requirements.py
homeassistant/setup.py
homeassistant/components/__init__.py
homeassistant/components/abode.py
homeassistant/components/alarmdecoder.py
homeassistant/components/alert.py
homeassistant/components/amcrest.py
homeassistant/components/android_ip_webcam.py
homeassistant/components/apcupsd.py
homeassistant/components/api.py
homeassistant/components/apple_tv.py
homeassistant/components/arduino.py
homeassistant/components/arlo.py
homeassistant/components/asterisk_mbox.py
homeassistant/components/august.py
homeassistant/components/axis.py
homeassistant/components/bbb_gpio.py
homeassistant/components/blink.py
homeassistant/components/bloomsky.py
homeassistant/components/bmw_connected_drive.py
homeassistant/components/browser.py
homeassistant/components/canary.py
homeassistant/components/coinbase.py
homeassistant/components/comfoconnect.py
homeassistant/components/config_entry_example.py
homeassistant/components/configurator.py
homeassistant/components/conversation.py
homeassistant/components/daikin.py
homeassistant/components/datadog.py
homeassistant/components/demo.py
homeassistant/components/device_sun_light_trigger.py
homeassistant/components/dialogflow.py
homeassistant/components/digital_ocean.py
homeassistant/components/discovery.py
homeassistant/components/dominos.py
homeassistant/components/doorbird.py
homeassistant/components/downloader.py
homeassistant/components/duckdns.py
homeassistant/components/dweet.py
homeassistant/components/dyson.py
homeassistant/components/ecobee.py
homeassistant/components/egardia.py
homeassistant/components/eight_sleep.py
