Metadata-Version: 2.0
Name: hassmart-homeassistant
Version: 0.65.4
Summary: Open-source home automation platform running on Python 3.
Home-page: https://home-assistant.io/
Author: The Home Assistant Authors
Author-email: hello@home-assistant.io
License: Apache License 2.0
Download-URL: https://github.com/home-assistant/home-assistant/archive/0.65.4.zip
Keywords: home,automation
Platform: any
Classifier: Development Status :: 4 - Beta
Classifier: Intended Audience :: End Users/Desktop
Classifier: Intended Audience :: Developers
Classifier: License :: OSI Approved :: Apache Software License
Classifier: Operating System :: OS Independent
Classifier: Programming Language :: Python :: 3.5
Classifier: Programming Language :: Python :: 3.6
Classifier: Topic :: Home Automation
Requires-Python: >=3.5.3
Requires-Dist: requests (==2.18.4)
Requires-Dist: pyyaml (<4,>=3.11)
Requires-Dist: pytz (>=2017.02)
Requires-Dist: pip (>=8.0.3)
Requires-Dist: jinja2 (>=2.10)
Requires-Dist: voluptuous (==0.11.1)
Requires-Dist: typing (<4,>=3)
Requires-Dist: aiohttp (==3.0.6)
Requires-Dist: async-timeout (==2.0.0)
Requires-Dist: astral (==1.5)
Requires-Dist: certifi (>=2017.4.17)
Requires-Dist: attrs (==17.4.0)
